env_factory/__init__.py
env_factory/main.py
env_factory/exceptions/__init__.py
env_factory/exceptions/client_exceptions.py
env_factory-1.1.0.dist-info/METADATA
env_factory-1.1.0.dist-info/WHEEL
env_factory-1.1.0.dist-info/top_level.txt
env_factory-1.1.0.dist-info/RECORD
