Metadata-Version: 2.4
Name: env-factory
Version: 1.1.0
Summary: A flexible Python package for retrieving environment variables from multiple sources including local environment and AWS Secrets Manager
Author: Deepak M S
Author-email: deepakcoder80@gmail.com
License: MIT
Keywords: environment variables,aws secrets manager,configuration,secrets,env,dotenv
Classifier: Development Status :: 5 - Production/Stable
Classifier: Intended Audience :: Developers
Classifier: License :: OSI Approved :: MIT License
Classifier: Programming Language :: Python :: 3
Classifier: Programming Language :: Python :: 3.8
Classifier: Programming Language :: Python :: 3.9
Classifier: Programming Language :: Python :: 3.10
Classifier: Programming Language :: Python :: 3.11
Classifier: Programming Language :: Python :: 3.12
Classifier: Topic :: Software Development :: Libraries :: Python Modules
Classifier: Topic :: System :: Systems Administration
Classifier: Topic :: Security
Requires-Python: >=3.8
Requires-Dist: sm-env-read>=1.1.0
Requires-Dist: python-dotenv
Provides-Extra: dev
Requires-Dist: pytest>=7.0.0; extra == "dev"
Requires-Dist: pytest-cov>=4.0.0; extra == "dev"
Requires-Dist: black>=22.0.0; extra == "dev"
Requires-Dist: flake8>=5.0.0; extra == "dev"
Requires-Dist: mypy>=1.0.0; extra == "dev"
Provides-Extra: dotenv
Requires-Dist: python-dotenv>=1.0.0; extra == "dotenv"
Provides-Extra: sm-env-read
Requires-Dist: sm-env-read>=1.1.0; extra == "sm-env-read"
Dynamic: author
Dynamic: author-email
Dynamic: classifier
Dynamic: description
Dynamic: description-content-type
Dynamic: keywords
Dynamic: license
Dynamic: provides-extra
Dynamic: requires-dist
Dynamic: requires-python
Dynamic: summary
